{
  "credit": "Made with Blockbench",
  "textures": {
    "0": "trapexpansion:block/spike_trap_base_bottom",
    "1": "trapexpansion:block/spike_trap_base",
    "particle": "trapexpansion:block/spike_trap_base_bottom"
  },
  "elements": [
    {
      "name": "base",
      "from": [0, 0, 0],
      "to": [16, 1, 16],
      "rotation": {"angle": 0, "axis": "z", "origin": [8, 8, 8]},
      "faces": {
        "north": {"uv": [0, 0, 16, 1], "texture": "#0"},
        "east": {"uv": [0, 0, 16, 1], "texture": "#0"},
        "south": {"uv": [0, 0, 16, 1], "texture": "#0"},
        "west": {"uv": [0, 0, 16, 1], "texture": "#0"},
        "up": {"uv": [0, 0, 16, 16], "texture": "#1"},
        "down": {"uv": [0, 0, 16, 16], "texture": "#0"}
      }
    }
  ],
  "display": {
    "thirdperson_righthand": {
      "scale": [0.375, 0.375, 0.375],
      "rotation": [75, 45, 0],
      "translation": [0, 2.5, 0]
    },
    "thirdperson_lefthand": {
      "scale": [0.375, 0.375, 0.375],
      "rotation": [75, 45, 0],
      "translation": [0, 2.5, 0]
    },
    "firstperson_righthand": {
      "scale": [0.4, 0.4, 0.4],
      "rotation": [0, 45, 0],
      "translation": [0, 5.5, 0]
    },
    "firstperson_lefthand": {
      "scale": [0.4, 0.4, 0.4],
      "translation": [0, 5.5, 0],
      "rotation": [0, 225, 0]
    },
    "head": {
      "translation": [0, 13.5, 0]
    },
    "ground": {
      "scale": [0.25, 0.25, 0.25],
      "rotation": [0, 0, 0],
      "translation": [0, 3, 0]
    },
    "fixed": {
      "scale": [0.5, 0.5, 0.5],
      "rotation": [-90, 0, 0],
      "translation": [0, 0, -4.5]
    },
    "gui": {
      "scale": [0.625, 0.625, 0.625],
      "rotation": [30, 225, 0],
      "translation": [0, 3, 0]
    }
  }
}